{
  "options": [
    {
      "name": "Brands",
      "value": ""
    },
    { "name": "A. Lange & Söhne", "value": "A. Lange & Söhne" },
    { "name": "Audemars Piguet", "value": "Audemars Piguet" },
    { "name": "Avi-8", "value": "Avi-8" },
    { "name": "Ball", "value": "Ball" },
    { "name": "Baltic", "value": "Baltic" },
    { "name": "Bell & Ross", "value": "Bell & Ross" },
    { "name": "Blancpain", "value": "Blancpain" },
    { "name": "Borel", "value": "Borel" },
    { "name": "Bovet", "value": "Bovet" },
    { "name": "Breguet", "value": "Breguet" },
    { "name": "Breitling", "value": "Breitling" },
    { "name": "Bvlgari", "value": "Bvlgari" },
    { "name": "Bulova", "value": "Bulova" },
    { "name": "Cartier", "value": "Cartier" },
    { "name": "Cauny", "value": "Cauny" },
    { "name": "Casio", "value": "Casio" },
    { "name": "Certina", "value": "Certina" },
    { "name": "Chopard", "value": "Chopard" },
    { "name": "Christopher Ward", "value": "Christopher Ward" },
    { "name": "ChronoSwiss", "value": "ChronoSwiss" },

    { "name": "Cvstos", "value": "Cvstos" },
    { "name": "Citizen", "value": "Citizen" },

    { "name": "Credor", "value": "Credor" },
    { "name": "Cuervo y Sobrinos", "value": "Cuervo y Sobrinos" },
    { "name": "Czapek", "value": "Czapek" },
    { "name": "Dan Henry", "value": "Dan Henry" },
    { "name": "Doxa", "value": "Doxa" },
    { "name": "F.P.Journe", "value": "F.P.Journe" },
    { "name": "Fears", "value": "Fears" },
    { "name": "Fortis", "value": "Fortis" },
    { "name": "Frank Muller", "value": "Frank Muller" },
    { "name": "Frederique Constant", "value": "Frederique Constant" },
    { "name": "Girrard-Perregaux", "value": "Girrard-Perregaux" },
    { "name": "Glashütte Original", "value": "Glashütte Original" },
    { "name": "Glycine", "value": "Glycine" },
    { "name": "GrandSeiko", "value": "Grandseiko" },
    { "name": "H.Moser & Cie", "value": "H.Moser & Cie" },
    { "name": "Hamilton", "value": "Hamilton" },
    { "name": "Hanhart", "value": "Hanhart" },
    { "name": "Hublot", "value": "hublot" },
    { "name": "Isotope", "value": "isotope" },
    { "name": "IWC", "value": "IWC" },
    { "name": "Jacob & Co.", "value": "Jacob & Co." },
    { "name": "Jeger-LeCoultre", "value": "Jeger-LeCoultre" },
    { "name": "Junghans", "value": "Junghans" },
    { "name": "Kurono Tokyo", "value": "Kurono Tokyo" },
    { "name": "Laco", "value": "Laco" },
    { "name": "Laurent Ferrier", "value": "Laurent Ferrier" },
    { "name": "Longines", "value": "Longines" },
    { "name": "Lorier", "value": "Lorier" },
    { "name": "Marathon", "value": "Marathon" },
    { "name": "Maurice Lacroix", "value": "Maurice Lacroix" },
    { "name": "Ming", "value": "Ming" },
    { "name": "Mondia", "value": "Mondia" },
    { "name": "Nixon", "value": "Nixon" },
    { "name": "Omega", "value": "Omega" },
    { "name": "Orient", "value": "Orient" },
    { "name": "Oris", "value": "Oris" },
    { "name": "Patek Philippe", "value": "Patek Philippe" },
    { "name": "Panerai", "value": "Panerai" },
    { "name": "Parmegiani Fleurier", "value": "Parmigiani Fleurier" },
    { "name": "Piaget", "value": "Piaget" },
    { "name": "Ressence", "value": "Ressence" },
    { "name": "Rolex", "value": "Rolex" },
    { "name": "Richard Mille", "value": "Richard Mille" },
    { "name": "Sandoz", "value": "Sandoz" },
    { "name": "Seiko", "value": "Seiko" },
    { "name": "Sicura", "value": "Sicura" },
    { "name": "Singer Reimagined", "value": "Singer Reimagined" },
    { "name": "Sinn", "value": "sinn" },
    { "name": "Steinhart", "value": "Steinhart" },
    { "name": "Stowa", "value": "Stowa" },
    { "name": "Tag Heur", "value": "Tag Heur" },
    { "name": "Timex", "value": "Timex" },
    { "name": "Tissot", "value": "Tissot" },
    { "name": "Tudor", "value": "Tudor" },
    { "name": "Ulysse Nardin", "value": "Ulysse Nardin" },
    { "name": "Universal Geneve", "value": "Universal Geneve" },
    { "name": "Urwerk", "value": "Urwerk" },
    { "name": "Vacheron Constatin", "value": "Vacheron Constatin" },
    { "name": "Victorinox", "value": "Victorinox" },
    { "name": "Yema", "value": "Yema" },
    { "name": "Zenith", "value": "Zenith" },
    { "name": "Zodiac", "value": "Zodiac" }
  ]
}
